canuvit/__init__.py
canuvit/__main__.py
canuvit/_canuvit_version.py
canuvit/canuvit.py
canuvit/cli.py
canuvit-0.5.1.dist-info/LICENSE
canuvit-0.5.1.dist-info/METADATA
canuvit-0.5.1.dist-info/WHEEL
canuvit-0.5.1.dist-info/entry_points.txt
canuvit-0.5.1.dist-info/top_level.txt
canuvit-0.5.1.dist-info/RECORD
