Metadata-Version: 2.1
Name: canuvit
Version: 0.5.1
Summary: UVIT safety checks
Home-page: https://github.com/prajwel/canuvit
Author: Prajwel Joseph
Author-email: prajwel.pj@gmail.com
Project-URL: Bug Tracker, https://github.com/prajwel/canuvit/issues
Classifier: Programming Language :: Python :: 3
Classifier: License :: OSI Approved :: Apache Software License
Classifier: Operating System :: OS Independent
Requires-Python: >=3.6
License-File: LICENSE
Requires-Dist: requests >=2
Requires-Dist: numpy >=1.13
Requires-Dist: matplotlib >=2
Requires-Dist: astropy >=2
Requires-Dist: beautifulsoup4 >=4.4
Requires-Dist: click >=2
Requires-Dist: astroquery >=0.4.5
